cpp26_equality_linter/__init__.py
cpp26_equality_linter/main.py
cpp26_equality_linter/prompts.py
cpp26_equality_linter-2025.12.20185334.dist-info/METADATA
cpp26_equality_linter-2025.12.20185334.dist-info/WHEEL
cpp26_equality_linter-2025.12.20185334.dist-info/top_level.txt
cpp26_equality_linter-2025.12.20185334.dist-info/RECORD
