Metadata-Version: 2.4
Name: cpp26-equality-linter
Version: 2025.12.20185334
Summary: A new package that automates equality checks in C++ code by leveraging the upcoming reflection capabilities in C++26. This tool will allow developers to input C++ code snippets or class definitions, a
Author-email: cpp26-equality-linter <hi@eugene.plus>
License: MIT
Project-URL: Homepage, https://github.com/chigwell/cpp26-equality-linter
Requires-Python: >=3.9
Requires-Dist: langchain-llm7>=0.0.0
Requires-Dist: llmatch-messages>=0.0.0
Requires-Dist: langchain-core>=0.3.0
